{
  "runNonce": "7f3cf3d4",
  "mode": "POSTS_ONLY",
  "batchCap": 100,
  "soakCycles": 100,
  "successCycles": 33,
  "completedCycles": 71,
  "inProgress": true,
  "synthesisEnabled": true,
  "totalSats": 3753407,
  "totalProofs": 3048,
  "satsPerProofAvg": 1231,
  "avgCycleSats": 113740,
  "avgCycleWallSec": 148,
  "totalWallSec": 40556,
  "fatalError": null,
  "cycles": [
    {
      "cycleIdx": 0,
      "error": "cycle 7f3cf3d4-000: worker proof not found before deadline"
    },
    {
      "cycleIdx": 1,
      "cycleId": "7f3cf3d4-001",
      "recordCount": 100,
      "scrapeWallMs": 15,
      "captainTaskId": "fe447fdb-8465-44bf-9ce5-1c1aa9e8895a",
      "captainIter": 2,
      "captainSats": 121443,
      "workerTaskId": "565372ac-9f0a-4bc5-81e8-4aed1cea0616",
      "workerSats": 13870,
      "proofsCreated": 100,
      "proofErrors": 0,
      "firstTxid": "4a5fe1d8162dd29ede23132e2d8ff7f27dcf1f7d647925d36fffa412d33e36e7",
      "lastTxid": "1034221b1564567a47e88c1c8e65b7136409c62fcb0be67c70cbe89f6cd07b1f",
      "manifestSha256": "2079399532a86bc1c84fb77c978d307ebf40f6c8db251c803b9610f2ff1f3adc",
      "synthesisTaskId": null,
      "synthesisSats": 0,
      "nanostoreUrl": null,
      "txidsUrl": null,
      "annotatedCount": 100,
      "totalSats": 135313,
      "satsPerProof": 1353,
      "cycleWallMs": 240914,
      "cycleWallSec": 241
    },
    {
      "cycleIdx": 2,
      "cycleId": "7f3cf3d4-002",
      "recordCount": 100,
      "scrapeWallMs": 13,
      "captainTaskId": "d57e5756-e1d7-4e2c-9f8e-e54bb3b58c95",
      "captainIter": 2,
      "captainSats": 95474,
      "workerTaskId": "565372ac-9f0a-4bc5-81e8-4aed1cea0616",
      "workerSats": 13870,
      "proofsCreated": 100,
      "proofErrors": 0,
      "firstTxid": "4a5fe1d8162dd29ede23132e2d8ff7f27dcf1f7d647925d36fffa412d33e36e7",
      "lastTxid": "1034221b1564567a47e88c1c8e65b7136409c62fcb0be67c70cbe89f6cd07b1f",
      "manifestSha256": "2079399532a86bc1c84fb77c978d307ebf40f6c8db251c803b9610f2ff1f3adc",
      "synthesisTaskId": null,
      "synthesisSats": 0,
      "nanostoreUrl": null,
      "txidsUrl": null,
      "annotatedCount": 100,
      "totalSats": 109344,
      "satsPerProof": 1093,
      "cycleWallMs": 103133,
      "cycleWallSec": 103
    },
    {
      "cycleIdx": 3,
      "cycleId": "7f3cf3d4-003",
      "recordCount": 100,
      "scrapeWallMs": 16,
      "captainTaskId": "da578700-ad97-40a7-84fd-0134b09be762",
      "captainIter": 2,
      "captainSats": 96540,
      "workerTaskId": "90fc585c-0c04-43c7-a55b-d064d356a6dd",
      "workerSats": 13926,
      "proofsCreated": 99,
      "proofErrors": 1,
      "firstTxid": "57c1fc5a25c0a64539c5835b4653433208393908ceef52e218dd634436c5275e",
      "lastTxid": "4f5370d7a5a2b87ae250a577208abf4dd6cb25a384eb253557ecd3838a3d66e3",
      "manifestSha256": "19f7d9b042ce9d840d749214c43229a46dfad3fe99d1f0755459e954513eefa5",
      "synthesisTaskId": null,
      "synthesisSats": 0,
      "nanostoreUrl": null,
      "txidsUrl": null,
      "annotatedCount": 99,
      "totalSats": 110466,
      "satsPerProof": 1116,
      "cycleWallMs": 216216,
      "cycleWallSec": 216
    },
    {
      "cycleIdx": 4,
      "cycleId": "7f3cf3d4-004",
      "recordCount": 100,
      "scrapeWallMs": 14,
      "captainTaskId": "0252dba2-0aef-4089-a56b-88fb90236fa8",
      "captainIter": 2,
      "captainSats": 107341,
      "workerTaskId": "4fd23ad5-a4c4-44fa-8f0b-9bdf2e9a0e46",
      "workerSats": 13983,
      "proofsCreated": 100,
      "proofErrors": 0,
      "firstTxid": "2e3a35fe55d3ab43fd86f93229072628e9a625128e13faae2cc2998ac6a1e358",
      "lastTxid": "38549889dcaa5f0e73957f0adbfc718899744b2da4f2960f06c8f4d95fcf6110",
      "manifestSha256": "ffc5536d3aa00aa442260cda2d7b6a43da8f3f62f14071b4974279c3567a518c",
      "synthesisTaskId": null,
      "synthesisSats": 0,
      "nanostoreUrl": null,
      "txidsUrl": null,
      "annotatedCount": 100,
      "totalSats": 121324,
      "satsPerProof": 1213,
      "cycleWallMs": 101043,
      "cycleWallSec": 101
    },
    {
      "cycleIdx": 5,
      "cycleId": "7f3cf3d4-005",
      "recordCount": 100,
      "scrapeWallMs": 13,
      "captainTaskId": "c6774e38-d503-47bd-aa4c-dd63c1be776b",
      "captainIter": 2,
      "captainSats": 111513,
      "workerTaskId": "a8585069-6976-4a6c-83e2-7809927497dc",
      "workerSats": 13931,
      "proofsCreated": 100,
      "proofErrors": 0,
      "firstTxid": "caadd6069a441f1aa54af2ff91ea9e2508f92715c6ae799a6435776d7db68a79",
      "lastTxid": "b8454f0c66fd31794a4cf51e937d7473309c358986fd8d18e013605b6cc6dc8b",
      "manifestSha256": "47d91bec9a3af057f8a9c0e956c53bd731a05772f01e324a4e10dbd64e1b3c51",
      "synthesisTaskId": null,
      "synthesisSats": 0,
      "nanostoreUrl": null,
      "txidsUrl": null,
      "annotatedCount": 100,
      "totalSats": 125444,
      "satsPerProof": 1254,
      "cycleWallMs": 167246,
      "cycleWallSec": 167
    },
    {
      "cycleIdx": 6,
      "cycleId": "7f3cf3d4-006",
      "recordCount": 100,
      "scrapeWallMs": 12,
      "captainTaskId": "cb86e58a-4609-4c68-a985-49c82fe49d3c",
      "captainIter": 2,
      "captainSats": 101377,
      "workerTaskId": "fcb7cc6a-16b0-4d14-b06e-0eac55071d2a",
      "workerSats": 12664,
      "proofsCreated": 100,
      "proofErrors": 0,
      "firstTxid": "bfe57453f2639f4df9ac20b3dc01db28b0cf8773b408701ce6b09fa91b1b12eb",
      "lastTxid": "9e324b52f1733c1a496b37fc9a9e65a10dcb932826fda41e4176768d54a87d75",
      "manifestSha256": "082e4a801773d48ea8c63c8b7b744459b40642913387a3eab7c7f5e8f93dc537",
      "synthesisTaskId": null,
      "synthesisSats": 0,
      "nanostoreUrl": null,
      "txidsUrl": null,
      "annotatedCount": 100,
      "totalSats": 114041,
      "satsPerProof": 1140,
      "cycleWallMs": 191560,
      "cycleWallSec": 192
    },
    {
      "cycleIdx": 7,
      "cycleId": "7f3cf3d4-007",
      "recordCount": 100,
      "scrapeWallMs": 17,
      "captainTaskId": "16089e4d-b95a-472d-ad5c-80086924ab11",
      "captainIter": 2,
      "captainSats": 109696,
      "workerTaskId": "a3e4f32d-2c66-42db-8f04-925ad2e1e891",
      "workerSats": 13623,
      "proofsCreated": 99,
      "proofErrors": 1,
      "firstTxid": "6041b1389846263de1d9adba65e64431e107f81907fe97b00fccd2994cf4b9fe",
      "lastTxid": "d43881457aa93b5fe17d9829a36aa91a4699b150556094a61fc1a071be5352f7",
      "manifestSha256": "dfc535340f2350b54d85456d7e3971d9781841dddd07b56f46332068bd92756d",
      "synthesisTaskId": null,
      "synthesisSats": 0,
      "nanostoreUrl": null,
      "txidsUrl": null,
      "annotatedCount": 99,
      "totalSats": 123319,
      "satsPerProof": 1246,
      "cycleWallMs": 157914,
      "cycleWallSec": 158
    },
    {
      "cycleIdx": 8,
      "cycleId": "7f3cf3d4-008",
      "recordCount": 100,
      "scrapeWallMs": 13,
      "captainTaskId": "18c5daf4-5680-42ba-9068-d662dd33a3d2",
      "captainIter": 2,
      "captainSats": 114790,
      "workerTaskId": "a3e4f32d-2c66-42db-8f04-925ad2e1e891",
      "workerSats": 13623,
      "proofsCreated": 99,
      "proofErrors": 1,
      "firstTxid": "6041b1389846263de1d9adba65e64431e107f81907fe97b00fccd2994cf4b9fe",
      "lastTxid": "d43881457aa93b5fe17d9829a36aa91a4699b150556094a61fc1a071be5352f7",
      "manifestSha256": "dfc535340f2350b54d85456d7e3971d9781841dddd07b56f46332068bd92756d",
      "synthesisTaskId": null,
      "synthesisSats": 0,
      "nanostoreUrl": null,
      "txidsUrl": null,
      "annotatedCount": 99,
      "totalSats": 128413,
      "satsPerProof": 1297,
      "cycleWallMs": 136004,
      "cycleWallSec": 136
    },
    {
      "cycleIdx": 9,
      "cycleId": "7f3cf3d4-009",
      "recordCount": 100,
      "scrapeWallMs": 12,
      "captainTaskId": "fb073e4a-9014-4118-b736-921a2140c0a9",
      "captainIter": 2,
      "captainSats": 107675,
      "workerTaskId": "707dc1e2-fd38-44a9-825f-491f3fd9e99f",
      "workerSats": 14357,
      "proofsCreated": 100,
      "proofErrors": 0,
      "firstTxid": "df9888fb128197b7469126cc791a6f69d07f758c739c89aa02d10dc581375100",
      "lastTxid": "60f0d5f8669b1867a71edcfe6b17be200138e724600230ea985ead0cfa21b5f3",
      "manifestSha256": "41c5652631e22c6f920c1cee93df226a9eaa931a9af1d80a8529f81263bd83d3",
      "synthesisTaskId": null,
      "synthesisSats": 0,
      "nanostoreUrl": null,
      "txidsUrl": null,
      "annotatedCount": 100,
      "totalSats": 122032,
      "satsPerProof": 1220,
      "cycleWallMs": 201909,
      "cycleWallSec": 202
    },
    {
      "cycleIdx": 10,
      "cycleId": "7f3cf3d4-010",
      "recordCount": 100,
      "scrapeWallMs": 13,
      "captainTaskId": "a4c91a0d-10cf-4930-a87a-f338c045c92f",
      "captainIter": 1,
      "captainSats": 1800,
      "workerTaskId": "a1f7008c-a51f-4ef6-b5a8-62efe94247bc",
      "workerSats": 14173,
      "proofsCreated": 100,
      "proofErrors": 0,
      "firstTxid": "7051160fd6b5f552e63cf2cba366a25bd6485af4cbad06c1ee036744a6d7ba4f",
      "lastTxid": "56fdc1dac9c27aa34c27b31cd1b72f06ed741fd5f65da2d3d443736a9c9763c1",
      "manifestSha256": "e1a4453898804e1e7eef94e6ce1924e010e72740b08be1ffc9dacf9179d2badc",
      "synthesisTaskId": null,
      "synthesisSats": 0,
      "nanostoreUrl": null,
      "txidsUrl": null,
      "annotatedCount": 100,
      "totalSats": 15973,
      "satsPerProof": 160,
      "cycleWallMs": 54545,
      "cycleWallSec": 55
    },
    {
      "cycleIdx": 11,
      "cycleId": "7f3cf3d4-011",
      "recordCount": 100,
      "scrapeWallMs": 11,
      "captainTaskId": "47a6484c-0b5a-4879-b2b8-c2399614e866",
      "captainIter": 1,
      "captainSats": 1800,
      "workerTaskId": "a1f7008c-a51f-4ef6-b5a8-62efe94247bc",
      "workerSats": 14173,
      "proofsCreated": 100,
      "proofErrors": 0,
      "firstTxid": "7051160fd6b5f552e63cf2cba366a25bd6485af4cbad06c1ee036744a6d7ba4f",
      "lastTxid": "56fdc1dac9c27aa34c27b31cd1b72f06ed741fd5f65da2d3d443736a9c9763c1",
      "manifestSha256": "e1a4453898804e1e7eef94e6ce1924e010e72740b08be1ffc9dacf9179d2badc",
      "synthesisTaskId": null,
      "synthesisSats": 0,
      "nanostoreUrl": null,
      "txidsUrl": null,
      "annotatedCount": 100,
      "totalSats": 15973,
      "satsPerProof": 160,
      "cycleWallMs": 30571,
      "cycleWallSec": 31
    },
    {
      "cycleIdx": 12,
      "cycleId": "7f3cf3d4-012",
      "recordCount": 100,
      "scrapeWallMs": 12,
      "captainTaskId": "2877ce9f-c14b-4fc9-9d0e-6151a24081fe",
      "captainIter": 1,
      "captainSats": 1800,
      "workerTaskId": "32775e8a-7730-4586-bf07-dd27e58b5b64",
      "workerSats": 16000,
      "proofsCreated": 100,
      "proofErrors": 0,
      "firstTxid": "24b3c7acce75055fee09920a3d3b50c7d8ab72bf840cb0a8cf6b361cc219c097",
      "lastTxid": "791425d956e5b649e75d12a8b028268a1f30f162d18880533b63f2b54ee0a866",
      "manifestSha256": "88029cd6a774c786760e172ad1431130aed11ce415f0ed5434f20ee004a7024a",
      "synthesisTaskId": null,
      "synthesisSats": 0,
      "nanostoreUrl": null,
      "txidsUrl": null,
      "annotatedCount": 100,
      "totalSats": 17800,
      "satsPerProof": 178,
      "cycleWallMs": 42540,
      "cycleWallSec": 43
    },
    {
      "cycleIdx": 13,
      "cycleId": "7f3cf3d4-013",
      "recordCount": 100,
      "scrapeWallMs": 13,
      "captainTaskId": "52673f14-2d39-4d5a-a597-82eaa129329b",
      "captainIter": 1,
      "captainSats": 1800,
      "workerTaskId": "32775e8a-7730-4586-bf07-dd27e58b5b64",
      "workerSats": 16000,
      "proofsCreated": 100,
      "proofErrors": 0,
      "firstTxid": "24b3c7acce75055fee09920a3d3b50c7d8ab72bf840cb0a8cf6b361cc219c097",
      "lastTxid": "791425d956e5b649e75d12a8b028268a1f30f162d18880533b63f2b54ee0a866",
      "manifestSha256": "88029cd6a774c786760e172ad1431130aed11ce415f0ed5434f20ee004a7024a",
      "synthesisTaskId": null,
      "synthesisSats": 0,
      "nanostoreUrl": null,
      "txidsUrl": null,
      "annotatedCount": 100,
      "totalSats": 17800,
      "satsPerProof": 178,
      "cycleWallMs": 30586,
      "cycleWallSec": 31
    },
    {
      "cycleIdx": 14,
      "error": "cycle 7f3cf3d4-014: worker proof not found before deadline"
    },
    {
      "cycleIdx": 15,
      "cycleId": "7f3cf3d4-015",
      "recordCount": 100,
      "scrapeWallMs": 28,
      "captainTaskId": "b2481abf-2830-4ffc-b48b-6d2ce1bb8035",
      "captainIter": 2,
      "captainSats": 107281,
      "workerTaskId": "840c0761-fb8b-46d8-a584-5487d17b2de4",
      "workerSats": 63219,
      "proofsCreated": 98,
      "proofErrors": 2,
      "firstTxid": "ac87d09be837b463b7cfe316351f189c2a2093b343789726809022ade392fea1",
      "lastTxid": "8090a6d8fbbde3fff6b0ba9d1aadf56cc01ee3cbbc6f47df6922a2c23de3b1d7",
      "manifestSha256": "579dd20ee4dec4968d04d8e91d120c77ab8946ca990acd2d523a98b12bf1f438",
      "synthesisTaskId": "33a41328-4fcd-47da-a8a8-8c40563bb602",
      "synthesisSats": 110349,
      "nanostoreUrl": null,
      "txidsUrl": null,
      "annotatedCount": 98,
      "totalSats": 280849,
      "satsPerProof": 2866,
      "cycleWallMs": 475677,
      "cycleWallSec": 476
    },
    {
      "cycleIdx": 16,
      "error": "cycle 7f3cf3d4-016: worker proof not found before deadline"
    },
    {
      "cycleIdx": 17,
      "error": "cycle 7f3cf3d4-017: worker proof not found before deadline"
    },
    {
      "cycleIdx": 18,
      "error": "cycle 7f3cf3d4-018: worker proof not found before deadline"
    },
    {
      "cycleIdx": 19,
      "error": "cycle 7f3cf3d4-019: worker proof not found before deadline"
    },
    {
      "cycleIdx": 20,
      "cycleId": "7f3cf3d4-020",
      "recordCount": 100,
      "scrapeWallMs": 97,
      "captainTaskId": "224455ce-c827-456d-8c2e-ce2abaf5ee56",
      "captainIter": 2,
      "captainSats": 118866,
      "workerTaskId": "3cc1e36e-659e-4d84-a608-22759e7c4d46",
      "workerSats": 56552,
      "proofsCreated": 56,
      "proofErrors": 44,
      "firstTxid": "f908dacf337a8353743cc6eae6b8a33e196478b5330e7971a4384e6ddac66ac7",
      "lastTxid": "b9a7b6ba3c5e3390c0cbfc90ccde0b6ee1bb44d1d758453318eb2eb93efc31bd",
      "manifestSha256": "39ac4d7f629046da940e004724725abeabf6754642cec00f0a583e37861c6761",
      "synthesisTaskId": null,
      "synthesisSats": 0,
      "nanostoreUrl": null,
      "txidsUrl": null,
      "annotatedCount": 56,
      "totalSats": 175418,
      "satsPerProof": 3132,
      "cycleWallMs": 134922,
      "cycleWallSec": 135
    },
    {
      "cycleIdx": 21,
      "error": "cycle 7f3cf3d4-021: worker proof not found before deadline"
    },
    {
      "cycleIdx": 22,
      "error": "cycle 7f3cf3d4-022: worker proof not found before deadline"
    },
    {
      "cycleIdx": 23,
      "cycleId": "7f3cf3d4-023",
      "recordCount": 100,
      "scrapeWallMs": 117,
      "captainTaskId": "28763f5e-a5e5-43b3-a2fd-8c2b976a26e4",
      "captainIter": 2,
      "captainSats": 113633,
      "workerTaskId": "8628bd34-5072-4e32-9aa0-c6b3a81931d1",
      "workerSats": 15161,
      "proofsCreated": 99,
      "proofErrors": 1,
      "firstTxid": "b6e0ac53d6103bf5ad9090b78b0a2d80649f4ec20d0e7255d2f4d5bacefdc089",
      "lastTxid": "d5c585fa2002fc7610be2b90717364fc48287d6d05ff3ff8dd449968957310c1",
      "manifestSha256": "7d01f0896b25d778a74d832bfa189c2c208fefe0619304f2838f0e823a193b39",
      "synthesisTaskId": null,
      "synthesisSats": 0,
      "nanostoreUrl": null,
      "txidsUrl": null,
      "annotatedCount": 99,
      "totalSats": 128794,
      "satsPerProof": 1301,
      "cycleWallMs": 310800,
      "cycleWallSec": 311
    },
    {
      "cycleIdx": 24,
      "cycleId": "7f3cf3d4-024",
      "recordCount": 100,
      "scrapeWallMs": 110,
      "captainTaskId": "41f81d4f-cc84-4e8f-96d2-d94fc5485e82",
      "captainIter": 2,
      "captainSats": 112233,
      "workerTaskId": "8628bd34-5072-4e32-9aa0-c6b3a81931d1",
      "workerSats": 15161,
      "proofsCreated": 99,
      "proofErrors": 1,
      "firstTxid": "b6e0ac53d6103bf5ad9090b78b0a2d80649f4ec20d0e7255d2f4d5bacefdc089",
      "lastTxid": "d5c585fa2002fc7610be2b90717364fc48287d6d05ff3ff8dd449968957310c1",
      "manifestSha256": "7d01f0896b25d778a74d832bfa189c2c208fefe0619304f2838f0e823a193b39",
      "synthesisTaskId": null,
      "synthesisSats": 0,
      "nanostoreUrl": null,
      "txidsUrl": null,
      "annotatedCount": 99,
      "totalSats": 127394,
      "satsPerProof": 1287,
      "cycleWallMs": 76726,
      "cycleWallSec": 77
    },
    {
      "cycleIdx": 25,
      "cycleId": "7f3cf3d4-025",
      "recordCount": 100,
      "scrapeWallMs": 92,
      "captainTaskId": "9c8352d6-8dfc-41e3-8d62-ff9ca09e0901",
      "captainIter": 2,
      "captainSats": 132081,
      "workerTaskId": "560c719f-dc81-4aaf-acf7-5137587daccc",
      "workerSats": 5771,
      "proofsCreated": 95,
      "proofErrors": 5,
      "firstTxid": "b0b5f498f972ad213305633e13e69774f72058cfd563259c5c66beddd8dd0f8b",
      "lastTxid": "0a5d5a09066807a6ade9c519f0980a17ea83668939a3c4329bc2be971c1bb345",
      "manifestSha256": "81cf34396b30b8425809961b3f7721e0a16bd20f904dc7913b0114aa49bba6ab",
      "synthesisTaskId": null,
      "synthesisSats": 0,
      "nanostoreUrl": null,
      "txidsUrl": null,
      "annotatedCount": 95,
      "totalSats": 137852,
      "satsPerProof": 1451,
      "cycleWallMs": 206708,
      "cycleWallSec": 207
    },
    {
      "cycleIdx": 26,
      "cycleId": "7f3cf3d4-026",
      "recordCount": 100,
      "scrapeWallMs": 128,
      "captainTaskId": "a92844c4-4c60-40bc-9e00-1ec1e9b75a04",
      "captainIter": 2,
      "captainSats": 126477,
      "workerTaskId": "a0c88ac2-7cfb-4767-8417-5ca0c42526a1",
      "workerSats": 6191,
      "proofsCreated": 43,
      "proofErrors": 57,
      "firstTxid": "08c91858d545dcfde5ebc24020ec492b1ab679d7965fea2d07858e4cb66a3163",
      "lastTxid": "3e699bc77597023cb90e8ee53d4f9b54599d84db7e077549dc89cf30c47b4022",
      "manifestSha256": "7dea4903d4732aa46215496b835ecc357e1c2a1cf3b8e11f5fa90e160b45c37e",
      "synthesisTaskId": null,
      "synthesisSats": 0,
      "nanostoreUrl": null,
      "txidsUrl": null,
      "annotatedCount": 43,
      "totalSats": 132668,
      "satsPerProof": 3085,
      "cycleWallMs": 86009,
      "cycleWallSec": 86
    },
    {
      "cycleIdx": 27,
      "error": "cycle 7f3cf3d4-027: worker proof not found before deadline"
    },
    {
      "cycleIdx": 28,
      "error": "cycle 7f3cf3d4-028: worker proof not found before deadline"
    },
    {
      "cycleIdx": 29,
      "cycleId": "7f3cf3d4-029",
      "recordCount": 100,
      "scrapeWallMs": 21,
      "captainTaskId": "6b9439e6-056a-44ed-be5f-77975afaadc3",
      "captainIter": 2,
      "captainSats": 125212,
      "workerTaskId": "5c61cbb0-931b-4912-b629-bfeea4132d35",
      "workerSats": 16364,
      "proofsCreated": 100,
      "proofErrors": 0,
      "firstTxid": "c48ef55b497ee7c1b00c6aa835c08ab533376844b604fcf4a0d8d6c7ae92c75a",
      "lastTxid": "101102fb04da1bce24194d1943241143952dc54497de23229b5898c27e34fa8a",
      "manifestSha256": "e90869e559b33c399b4b5359e2fc1a6b9707f4068c99402f18187fb19e8759a0",
      "synthesisTaskId": null,
      "synthesisSats": 0,
      "nanostoreUrl": null,
      "txidsUrl": null,
      "annotatedCount": 100,
      "totalSats": 141576,
      "satsPerProof": 1416,
      "cycleWallMs": 154775,
      "cycleWallSec": 155
    },
    {
      "cycleIdx": 30,
      "cycleId": "7f3cf3d4-030",
      "recordCount": 100,
      "scrapeWallMs": 14,
      "captainTaskId": "a7ec45e9-f005-4261-9fc6-66ec1efff444",
      "captainIter": 2,
      "captainSats": 105143,
      "workerTaskId": "5c61cbb0-931b-4912-b629-bfeea4132d35",
      "workerSats": 16364,
      "proofsCreated": 100,
      "proofErrors": 0,
      "firstTxid": "c48ef55b497ee7c1b00c6aa835c08ab533376844b604fcf4a0d8d6c7ae92c75a",
      "lastTxid": "101102fb04da1bce24194d1943241143952dc54497de23229b5898c27e34fa8a",
      "manifestSha256": "e90869e559b33c399b4b5359e2fc1a6b9707f4068c99402f18187fb19e8759a0",
      "synthesisTaskId": "2ee12c6a-dd3c-4cc6-8707-d5eb1045ac66",
      "synthesisSats": 600,
      "nanostoreUrl": null,
      "txidsUrl": null,
      "annotatedCount": 100,
      "totalSats": 122107,
      "satsPerProof": 1221,
      "cycleWallMs": 81892,
      "cycleWallSec": 82
    },
    {
      "cycleIdx": 31,
      "cycleId": "7f3cf3d4-031",
      "recordCount": 100,
      "scrapeWallMs": 66,
      "captainTaskId": "5dfb4cf1-4c20-4edc-b9e3-66b9e1e36e01",
      "captainIter": 1,
      "captainSats": 1800,
      "workerTaskId": "a3c9687f-744b-4e89-b740-dce1bc3e091d",
      "workerSats": 14135,
      "proofsCreated": 100,
      "proofErrors": 0,
      "firstTxid": "02cc3005fcaf48209b08a5126a533cb50ce2edad17cc234d90c7e7ee4bf69132",
      "lastTxid": "f01f5dc67a19d93b2bff780731c3c7347b7e1666ba3b16b88d91062791bb2edd",
      "manifestSha256": "5ccfae9c4602050dce9ff6744ba0b17c3f6fad9113bbf60d17f78eb171037eaa",
      "synthesisTaskId": null,
      "synthesisSats": 0,
      "nanostoreUrl": null,
      "txidsUrl": null,
      "annotatedCount": 100,
      "totalSats": 15935,
      "satsPerProof": 159,
      "cycleWallMs": 141487,
      "cycleWallSec": 141
    },
    {
      "cycleIdx": 32,
      "cycleId": "7f3cf3d4-032",
      "recordCount": 100,
      "scrapeWallMs": 24,
      "captainTaskId": "cfbe4d14-11fe-44fe-b7d9-82f006ecc976",
      "captainIter": 2,
      "captainSats": 122388,
      "workerTaskId": "a3c9687f-744b-4e89-b740-dce1bc3e091d",
      "workerSats": 14135,
      "proofsCreated": 100,
      "proofErrors": 0,
      "firstTxid": "02cc3005fcaf48209b08a5126a533cb50ce2edad17cc234d90c7e7ee4bf69132",
      "lastTxid": "f01f5dc67a19d93b2bff780731c3c7347b7e1666ba3b16b88d91062791bb2edd",
      "manifestSha256": "5ccfae9c4602050dce9ff6744ba0b17c3f6fad9113bbf60d17f78eb171037eaa",
      "synthesisTaskId": null,
      "synthesisSats": 0,
      "nanostoreUrl": null,
      "txidsUrl": null,
      "annotatedCount": 100,
      "totalSats": 136523,
      "satsPerProof": 1365,
      "cycleWallMs": 94674,
      "cycleWallSec": 95
    },
    {
      "cycleIdx": 33,
      "cycleId": "7f3cf3d4-033",
      "recordCount": 100,
      "scrapeWallMs": 12,
      "captainTaskId": "5a509fcc-1483-4af9-bb33-dd98d27497a4",
      "captainIter": 1,
      "captainSats": 1800,
      "workerTaskId": "959c689d-e313-4d02-9e11-467a69bb00bf",
      "workerSats": 14325,
      "proofsCreated": 100,
      "proofErrors": 0,
      "firstTxid": "75d510528e75deee9aa9babf5b1144454ea7c50fca74e2cd348d72cdc717fcb1",
      "lastTxid": "35257eeb47b609dcd21c5a5465b54acdc3c9f014fa6353d583af60b885cc4782",
      "manifestSha256": "9602a07a64858ae5d0af94f51a2c04f98c0469165a0776798957b72449d79b89",
      "synthesisTaskId": null,
      "synthesisSats": 0,
      "nanostoreUrl": null,
      "txidsUrl": null,
      "annotatedCount": 100,
      "totalSats": 16125,
      "satsPerProof": 161,
      "cycleWallMs": 96276,
      "cycleWallSec": 96
    },
    {
      "cycleIdx": 34,
      "error": "cycle 7f3cf3d4-034: worker proof not found before deadline"
    },
    {
      "cycleIdx": 35,
      "error": "cycle 7f3cf3d4-035: worker proof not found before deadline"
    },
    {
      "cycleIdx": 36,
      "cycleId": "7f3cf3d4-036",
      "recordCount": 100,
      "scrapeWallMs": 716,
      "captainTaskId": "3f48c560-e8b6-418d-9941-e6e921daf8a3",
      "captainIter": 2,
      "captainSats": 105194,
      "workerTaskId": "3425ca79-9c94-419a-a9f9-b53df950be5b",
      "workerSats": 6636,
      "proofsCreated": 83,
      "proofErrors": 17,
      "firstTxid": "fa1ae1c5be51d881c1a7303ffd5ae487a8fa3ae97840e7a6ca9bae5dd1593f7b",
      "lastTxid": "b3eeacdeca21b137732dd9f5bf5e60900d3bb333a9f9835dbf62fdafa14fa72d",
      "manifestSha256": "02460073de65bff55319e358d4f7a1d75bbea6cca89c72923f69a41c92974d60",
      "synthesisTaskId": null,
      "synthesisSats": 0,
      "nanostoreUrl": null,
      "txidsUrl": null,
      "annotatedCount": 83,
      "totalSats": 111830,
      "satsPerProof": 1347,
      "cycleWallMs": 222851,
      "cycleWallSec": 223
    },
    {
      "cycleIdx": 37,
      "error": "cycle 7f3cf3d4-037: worker proof not found before deadline"
    },
    {
      "cycleIdx": 38,
      "error": "cycle 7f3cf3d4-038: worker proof not found before deadline"
    },
    {
      "cycleIdx": 39,
      "error": "cycle 7f3cf3d4-039: worker proof not found before deadline"
    },
    {
      "cycleIdx": 40,
      "error": "cycle 7f3cf3d4-040: worker proof not found before deadline"
    },
    {
      "cycleIdx": 41,
      "cycleId": "7f3cf3d4-041",
      "recordCount": 100,
      "scrapeWallMs": 12,
      "captainTaskId": "270dc3d1-c106-467d-8175-05654c2119cf",
      "captainIter": 2,
      "captainSats": 125481,
      "workerTaskId": "aa0a2763-17fd-4f09-ab77-799e6b46dd2f",
      "workerSats": 17244,
      "proofsCreated": 100,
      "proofErrors": 0,
      "firstTxid": "694e9341947239506b912bdfa6188a1081aec667a98984b4694728e39c264948",
      "lastTxid": "96575353f472786400a342cc6c6c4f096aeb3a7a6b0e53efa0daa9bd91c9ee58",
      "manifestSha256": "37a2a2eecf66cc81fd5f074dfc4fec68deeabd5296a75661bd07b15dc45d816c",
      "synthesisTaskId": null,
      "synthesisSats": 0,
      "nanostoreUrl": null,
      "txidsUrl": null,
      "annotatedCount": 100,
      "totalSats": 142725,
      "satsPerProof": 1427,
      "cycleWallMs": 181753,
      "cycleWallSec": 182
    },
    {
      "cycleIdx": 42,
      "cycleId": "7f3cf3d4-042",
      "recordCount": 100,
      "scrapeWallMs": 11,
      "captainTaskId": "a76e6c09-50b5-4ad3-856e-b6155c3bbd4c",
      "captainIter": 2,
      "captainSats": 122774,
      "workerTaskId": "aa0a2763-17fd-4f09-ab77-799e6b46dd2f",
      "workerSats": 17244,
      "proofsCreated": 100,
      "proofErrors": 0,
      "firstTxid": "694e9341947239506b912bdfa6188a1081aec667a98984b4694728e39c264948",
      "lastTxid": "96575353f472786400a342cc6c6c4f096aeb3a7a6b0e53efa0daa9bd91c9ee58",
      "manifestSha256": "37a2a2eecf66cc81fd5f074dfc4fec68deeabd5296a75661bd07b15dc45d816c",
      "synthesisTaskId": null,
      "synthesisSats": 0,
      "nanostoreUrl": null,
      "txidsUrl": null,
      "annotatedCount": 100,
      "totalSats": 140018,
      "satsPerProof": 1400,
      "cycleWallMs": 79105,
      "cycleWallSec": 79
    },
    {
      "cycleIdx": 43,
      "cycleId": "7f3cf3d4-043",
      "recordCount": 100,
      "scrapeWallMs": 11,
      "captainTaskId": "93952674-4980-4a1b-8e4a-910ec07615fe",
      "captainIter": 2,
      "captainSats": 103870,
      "workerTaskId": "da15465a-c76a-4a8a-b893-81f4f53da202",
      "workerSats": 14027,
      "proofsCreated": 100,
      "proofErrors": 0,
      "firstTxid": "90a06cc5e00d23ed6b531adacc8062afa35e9b1fa1b03d0ff065eb86d9fdc48f",
      "lastTxid": "0e910d081dd7c7c3640198499bab36c0b2b0eb4fffbd5e389cf85fafbca83e56",
      "manifestSha256": "7a2a3c3adb635ffb3b2642bdb189570d74057741d2fec59b4bde6ca8136c505c",
      "synthesisTaskId": null,
      "synthesisSats": 0,
      "nanostoreUrl": null,
      "txidsUrl": null,
      "annotatedCount": 100,
      "totalSats": 117897,
      "satsPerProof": 1179,
      "cycleWallMs": 109325,
      "cycleWallSec": 109
    },
    {
      "cycleIdx": 44,
      "cycleId": "7f3cf3d4-044",
      "recordCount": 100,
      "scrapeWallMs": 12,
      "captainTaskId": "c270cf70-395b-4b14-926a-eb8253e4c727",
      "captainIter": 2,
      "captainSats": 98661,
      "workerTaskId": "ce391066-2ac5-438a-a6c5-dd7aabe7d113",
      "workerSats": 13225,
      "proofsCreated": 100,
      "proofErrors": 0,
      "firstTxid": "edee52dcab3f7150dbc3ff5ce1a3a60f120e10ac2ca110240cfb8982272769dd",
      "lastTxid": "693086a44b5782fd9fd0ddea3b14721e3a20db6e1747dfd17074fd8e08c5ffd4",
      "manifestSha256": "1dadc5fb3de1c9e9b67a1dfa528199f4221edda076a45e8970011f7cc181bfb5",
      "synthesisTaskId": null,
      "synthesisSats": 0,
      "nanostoreUrl": null,
      "txidsUrl": null,
      "annotatedCount": 100,
      "totalSats": 111886,
      "satsPerProof": 1119,
      "cycleWallMs": 54813,
      "cycleWallSec": 55
    },
    {
      "cycleIdx": 45,
      "cycleId": "7f3cf3d4-045",
      "recordCount": 100,
      "scrapeWallMs": 13,
      "captainTaskId": "b5a34d2e-480a-43a8-a844-15f92acc04c2",
      "captainIter": 2,
      "captainSats": 112662,
      "workerTaskId": "95e80739-d147-479c-9f7e-0e37de041613",
      "workerSats": 13878,
      "proofsCreated": 100,
      "proofErrors": 0,
      "firstTxid": "fab2a02b25f6faa9193c12f9de60057f1dc361b1d057f2602ba9570eb2b8a7b5",
      "lastTxid": "fc04ae2e624ab3b8a5ce0b2260fd6e2c042de62e19caa1228c2efc7a008a2cb9",
      "manifestSha256": "92c6366eea2c99a906ac0566b7c797343a70a1be73eb2124c8da1c248bf7f72a",
      "synthesisTaskId": "f6effec2-e533-414d-a9d4-fb6157335cda",
      "synthesisSats": 110083,
      "nanostoreUrl": null,
      "txidsUrl": null,
      "annotatedCount": 100,
      "totalSats": 236623,
      "satsPerProof": 2366,
      "cycleWallMs": 157908,
      "cycleWallSec": 158
    },
    {
      "cycleIdx": 46,
      "cycleId": "7f3cf3d4-046",
      "recordCount": 100,
      "scrapeWallMs": 13,
      "captainTaskId": "a348182d-2423-454c-8940-308a5655685d",
      "captainIter": 2,
      "captainSats": 106672,
      "workerTaskId": "680e00bf-4ba2-43dc-a39e-e5b9cf45420b",
      "workerSats": 14019,
      "proofsCreated": 100,
      "proofErrors": 0,
      "firstTxid": "d956daf6437495059432a6616cf9c318026cf0ffa3deeff278d46f2485f9916a",
      "lastTxid": "2bc63b2580fad7496ec1cb785251dbd46e5d893132840f6d0c7d902174c6274c",
      "manifestSha256": "538385a0e03d5dc2521a8a5b208e27c0368e1c3aadd27c2d4ad10266b61505db",
      "synthesisTaskId": null,
      "synthesisSats": 0,
      "nanostoreUrl": null,
      "txidsUrl": null,
      "annotatedCount": 100,
      "totalSats": 120691,
      "satsPerProof": 1207,
      "cycleWallMs": 88929,
      "cycleWallSec": 89
    },
    {
      "cycleIdx": 47,
      "error": "cycle 7f3cf3d4-047: worker proof not found before deadline"
    },
    {
      "cycleIdx": 48,
      "error": "cycle 7f3cf3d4-048: worker proof not found before deadline"
    },
    {
      "cycleIdx": 49,
      "cycleId": "7f3cf3d4-049",
      "recordCount": 100,
      "scrapeWallMs": 122,
      "captainTaskId": "bfea59cc-9271-41e5-8512-5459525f6d75",
      "captainIter": 2,
      "captainSats": 116727,
      "workerTaskId": "c0af480d-9071-4315-9d4f-b1b2b222c80c",
      "workerSats": 6339,
      "proofsCreated": 71,
      "proofErrors": 29,
      "firstTxid": "733e2f31da0cef7474b29dee8ec34a344af2bc0d9f50e2f5c1e2eca22735b758",
      "lastTxid": "9937530929894ab8bf95bdcb0285db2c1b178b727b752860772f7ef30a2ec994",
      "manifestSha256": "b58d8bc654168141f8c6373a2ef0368f5089f8e6e91c26dddfac746939a9609b",
      "synthesisTaskId": null,
      "synthesisSats": 0,
      "nanostoreUrl": null,
      "txidsUrl": null,
      "annotatedCount": 71,
      "totalSats": 123066,
      "satsPerProof": 1733,
      "cycleWallMs": 260272,
      "cycleWallSec": 260
    },
    {
      "cycleIdx": 50,
      "error": "cycle 7f3cf3d4-050: worker proof not found before deadline"
    },
    {
      "cycleIdx": 51,
      "error": "cycle 7f3cf3d4-051: worker proof not found before deadline"
    },
    {
      "cycleIdx": 52,
      "error": "cycle 7f3cf3d4-052: worker proof not found before deadline"
    },
    {
      "cycleIdx": 53,
      "error": "cycle 7f3cf3d4-053: worker proof not found before deadline"
    },
    {
      "cycleIdx": 54,
      "error": "cycle 7f3cf3d4-054: worker proof not found before deadline"
    },
    {
      "cycleIdx": 55,
      "cycleId": "7f3cf3d4-055",
      "recordCount": 100,
      "scrapeWallMs": 139,
      "captainTaskId": "061e9681-d8c2-4c75-9e51-d1b3a802ae15",
      "captainIter": 2,
      "captainSats": 69086,
      "workerTaskId": "49587bae-5c2f-4288-addf-5025ea3004da",
      "workerSats": 7102,
      "proofsCreated": 7,
      "proofErrors": 93,
      "firstTxid": "92714ac0b78bc090bc1c8f990ab60a143122cd14e7af55c807564760a008114f",
      "lastTxid": "89dd5ed14b87889d1b20d117abfbfc55e5d85d9b6859ac6761e7f7547fc7e7ae",
      "manifestSha256": "24c9c2300b53d7421c71d3ac71118574f666901a627fa4bb8673412caf30320c",
      "synthesisTaskId": null,
      "synthesisSats": 0,
      "nanostoreUrl": null,
      "txidsUrl": null,
      "annotatedCount": 7,
      "totalSats": 76188,
      "satsPerProof": 10884,
      "cycleWallMs": 199502,
      "cycleWallSec": 200
    },
    {
      "cycleIdx": 56,
      "error": "cycle 7f3cf3d4-056: worker proof not found before deadline"
    },
    {
      "cycleIdx": 57,
      "error": "cycle 7f3cf3d4-057: worker proof not found before deadline"
    },
    {
      "cycleIdx": 58,
      "error": "cycle 7f3cf3d4-058: worker proof not found before deadline"
    },
    {
      "cycleIdx": 59,
      "error": "cycle 7f3cf3d4-059: worker proof not found before deadline"
    },
    {
      "cycleIdx": 60,
      "error": "cycle 7f3cf3d4-060: worker proof not found before deadline"
    },
    {
      "cycleIdx": 61,
      "error": "cycle 7f3cf3d4-061: worker proof not found before deadline"
    },
    {
      "cycleIdx": 62,
      "error": "cycle 7f3cf3d4-062: worker proof not found before deadline"
    },
    {
      "cycleIdx": 63,
      "error": "cycle 7f3cf3d4-063: worker proof not found before deadline"
    },
    {
      "cycleIdx": 64,
      "error": "cycle 7f3cf3d4-064: worker proof not found before deadline"
    },
    {
      "cycleIdx": 65,
      "error": "cycle 7f3cf3d4-065: worker proof not found before deadline"
    },
    {
      "cycleIdx": 66,
      "error": "cycle 7f3cf3d4-066: worker proof not found before deadline"
    },
    {
      "cycleIdx": 67,
      "error": "cycle 7f3cf3d4-067: worker proof not found before deadline"
    },
    {
      "cycleIdx": 68,
      "error": "cycle 7f3cf3d4-068: worker proof not found before deadline"
    },
    {
      "cycleIdx": 69,
      "error": "cycle 7f3cf3d4-069: worker proof not found before deadline"
    },
    {
      "cycleIdx": 70,
      "error": "cycle 7f3cf3d4-070: worker proof not found before deadline"
    }
  ]
}