{
  "runNonce": "47b4da02",
  "mode": "POSTS_ONLY",
  "batchCap": 100,
  "soakCycles": 17,
  "successCycles": 17,
  "completedCycles": 17,
  "inProgress": false,
  "synthesisEnabled": true,
  "totalSats": 2424838,
  "totalProofs": 1699,
  "satsPerProofAvg": 1427,
  "avgCycleSats": 142638,
  "avgCycleWallSec": 145,
  "totalWallSec": 2474,
  "fatalError": null,
  "cycles": [
    {
      "cycleIdx": 0,
      "cycleId": "47b4da02-000",
      "recordCount": 100,
      "scrapeWallMs": 11,
      "captainTaskId": "13199b2a-56dc-44f7-bc5b-6d2c7c47ad61",
      "captainIter": 2,
      "captainSats": 104114,
      "workerTaskId": "03a3c543-d1ec-4f90-af92-5e6006cea520",
      "workerSats": 14010,
      "proofsCreated": 100,
      "proofErrors": 0,
      "firstTxid": "e49f226bed51af4fb32a25e43671f81f3c6e2fb0956e999ab83b1f58bc49eab3",
      "lastTxid": "eb1352031c89eacef935012327785277db836568eff7631d817f7c0d48b89caa",
      "manifestSha256": "ca529644191b8842eb1d63a6dcfdd793913e9c01e07b286c0054d07efeacb47b",
      "synthesisTaskId": "6cb3627e-adda-44ea-af12-e2bec97d09ac",
      "synthesisSats": 346883,
      "nanostoreUrl": "https://storage.googleapis.com/prod-uhrp/cdn/4tbnigCpdqPwfB7iPN4Cbp",
      "txidsUrl": "https://storage.googleapis.com/prod-uhrp/cdn/4RW3roa7R6J73aAuq5KQxS",
      "annotatedCount": 100,
      "totalSats": 465007,
      "satsPerProof": 4650,
      "cycleWallMs": 331014,
      "cycleWallSec": 331
    },
    {
      "cycleIdx": 1,
      "cycleId": "47b4da02-001",
      "recordCount": 100,
      "scrapeWallMs": 12,
      "captainTaskId": "d783d287-c925-4f84-b2a0-b51a6ad0ca05",
      "captainIter": 2,
      "captainSats": 122636,
      "workerTaskId": "c125faa9-dc4c-4e84-8dbc-7a8c279ab9dc",
      "workerSats": 14413,
      "proofsCreated": 100,
      "proofErrors": 0,
      "firstTxid": "4728e9b741d1051e44c4cc186b554a51d0e5febf6923bc59a8c15243dd01617d",
      "lastTxid": "63f4895617a331b947522da76daf76601ab641a883531de118cdf728ba8a3a5b",
      "manifestSha256": "d57ec35e9669f53f457baf2326728e07a0145a2435fae62108d3a12f9638c56e",
      "synthesisTaskId": null,
      "synthesisSats": 0,
      "nanostoreUrl": null,
      "txidsUrl": null,
      "annotatedCount": 100,
      "totalSats": 137049,
      "satsPerProof": 1370,
      "cycleWallMs": 146000,
      "cycleWallSec": 146
    },
    {
      "cycleIdx": 2,
      "cycleId": "47b4da02-002",
      "recordCount": 100,
      "scrapeWallMs": 12,
      "captainTaskId": "44b1fbc2-7aa9-4a9b-82a9-b2195e53e95a",
      "captainIter": 2,
      "captainSats": 111712,
      "workerTaskId": "6c7da551-b682-4152-ab21-7fb54ccbe235",
      "workerSats": 13567,
      "proofsCreated": 100,
      "proofErrors": 0,
      "firstTxid": "fd261387a14bf4a6d5fd505d48183586c706660f32812c521bbd06a4f15f136f",
      "lastTxid": "e61ae255dc8731c269389d8bc4fb1e8ba53f7959177f9c667e13786a70cbc93f",
      "manifestSha256": "a6370d6d0754ca99c610bd63e52095fd77263d4945809ccc67a7b01d278718a9",
      "synthesisTaskId": null,
      "synthesisSats": 0,
      "nanostoreUrl": null,
      "txidsUrl": null,
      "annotatedCount": 100,
      "totalSats": 125279,
      "satsPerProof": 1253,
      "cycleWallMs": 157100,
      "cycleWallSec": 157
    },
    {
      "cycleIdx": 3,
      "cycleId": "47b4da02-003",
      "recordCount": 100,
      "scrapeWallMs": 12,
      "captainTaskId": "44a79b18-987a-4091-8e5e-d6788a1fb06d",
      "captainIter": 2,
      "captainSats": 103261,
      "workerTaskId": "6c7da551-b682-4152-ab21-7fb54ccbe235",
      "workerSats": 13567,
      "proofsCreated": 100,
      "proofErrors": 0,
      "firstTxid": "fd261387a14bf4a6d5fd505d48183586c706660f32812c521bbd06a4f15f136f",
      "lastTxid": "e61ae255dc8731c269389d8bc4fb1e8ba53f7959177f9c667e13786a70cbc93f",
      "manifestSha256": "a6370d6d0754ca99c610bd63e52095fd77263d4945809ccc67a7b01d278718a9",
      "synthesisTaskId": null,
      "synthesisSats": 0,
      "nanostoreUrl": null,
      "txidsUrl": null,
      "annotatedCount": 100,
      "totalSats": 116828,
      "satsPerProof": 1168,
      "cycleWallMs": 121853,
      "cycleWallSec": 122
    },
    {
      "cycleIdx": 4,
      "cycleId": "47b4da02-004",
      "recordCount": 100,
      "scrapeWallMs": 10,
      "captainTaskId": "8e65ca45-feb1-4c17-b97d-d5dc9f9b8ec2",
      "captainIter": 2,
      "captainSats": 98199,
      "workerTaskId": "4816f46e-fc09-43d2-ae0d-b5962e66f90e",
      "workerSats": 16143,
      "proofsCreated": 100,
      "proofErrors": 0,
      "firstTxid": "cfb412f2f0e7a977ed3550f22b0c18957f1cbeb544487f035003f4f8187578ca",
      "lastTxid": "aac313f5af10513e2eaf4c464c671597c845c685fd1770f4b2df42d8f0261e5e",
      "manifestSha256": "8bc74dbf168355561beb4999e83c2a8dbd6583ca21b1f28315862c757265a166",
      "synthesisTaskId": null,
      "synthesisSats": 0,
      "nanostoreUrl": null,
      "txidsUrl": null,
      "annotatedCount": 100,
      "totalSats": 114342,
      "satsPerProof": 1143,
      "cycleWallMs": 85207,
      "cycleWallSec": 85
    },
    {
      "cycleIdx": 5,
      "cycleId": "47b4da02-005",
      "recordCount": 100,
      "scrapeWallMs": 11,
      "captainTaskId": "b35efd79-0fc9-45ed-9430-eb1ea7f919be",
      "captainIter": 2,
      "captainSats": 106215,
      "workerTaskId": "e7637966-155a-47db-a351-d2c2f78215ae",
      "workerSats": 14043,
      "proofsCreated": 100,
      "proofErrors": 0,
      "firstTxid": "668cf9be120e1bf60ebc904cb6d0e25ea0489e3bca98cd5f9c28e2c21bb493c1",
      "lastTxid": "411abdd386c83f63e4d4ac7307df4892a02a5d3036129c61973d7b2f9eb71cc7",
      "manifestSha256": "866c2df21296ecc5924e1232faadee257110976ec889f60414c09f525742bad3",
      "synthesisTaskId": null,
      "synthesisSats": 0,
      "nanostoreUrl": null,
      "txidsUrl": null,
      "annotatedCount": 100,
      "totalSats": 120258,
      "satsPerProof": 1203,
      "cycleWallMs": 133508,
      "cycleWallSec": 134
    },
    {
      "cycleIdx": 6,
      "cycleId": "47b4da02-006",
      "recordCount": 100,
      "scrapeWallMs": 11,
      "captainTaskId": "14348b61-46b2-437d-9832-84c651be6377",
      "captainIter": 2,
      "captainSats": 103144,
      "workerTaskId": "7359458e-22ac-446f-9aa6-f32aedbe6afa",
      "workerSats": 14684,
      "proofsCreated": 100,
      "proofErrors": 0,
      "firstTxid": "7c7ed7850255a7ed28be642bb6e69888cc6dc5f859126abe57041fdb0ad18d1d",
      "lastTxid": "f1e82fba3879ab3bb0a89d7ce0c08d5e177a1ba67cc5a7fd0676dd0fbaa648b0",
      "manifestSha256": "f169720603d8e845ee1907949dfbe87ac33aff5b29603eae9509876dca481a4a",
      "synthesisTaskId": null,
      "synthesisSats": 0,
      "nanostoreUrl": null,
      "txidsUrl": null,
      "annotatedCount": 100,
      "totalSats": 117828,
      "satsPerProof": 1178,
      "cycleWallMs": 139762,
      "cycleWallSec": 140
    },
    {
      "cycleIdx": 7,
      "cycleId": "47b4da02-007",
      "recordCount": 100,
      "scrapeWallMs": 11,
      "captainTaskId": "70e07795-f7e8-4722-bbcf-aaddcba090e7",
      "captainIter": 2,
      "captainSats": 121072,
      "workerTaskId": "f5473362-d121-4312-8d12-67419d09d827",
      "workerSats": 15701,
      "proofsCreated": 100,
      "proofErrors": 0,
      "firstTxid": "5b05e17183be86e7f7b902288ffc92a205d12c72c8303bcd3f77af8256af949d",
      "lastTxid": "7e0f79016039c237584b2d51a2618aac7725add17171e7d2c4079c524f62c9e9",
      "manifestSha256": "d4a273be48d03bd785aada7c0f67173efe9e78473be6955b688dc6f3ec2be872",
      "synthesisTaskId": null,
      "synthesisSats": 0,
      "nanostoreUrl": null,
      "txidsUrl": null,
      "annotatedCount": 100,
      "totalSats": 136773,
      "satsPerProof": 1368,
      "cycleWallMs": 131112,
      "cycleWallSec": 131
    },
    {
      "cycleIdx": 8,
      "cycleId": "47b4da02-008",
      "recordCount": 100,
      "scrapeWallMs": 11,
      "captainTaskId": "8152d356-50fb-4cef-9542-598ea4af5fe6",
      "captainIter": 2,
      "captainSats": 111207,
      "workerTaskId": "0268d5f9-654c-4a5f-bfda-5d29c2d60b0f",
      "workerSats": 14719,
      "proofsCreated": 100,
      "proofErrors": 0,
      "firstTxid": "4c015cd65628ad26eef1bafffe635c5b239fae860d4534a20cc11d4d31b8b5dd",
      "lastTxid": "0f6072605bdb3f2a4f843ef98b963061f4bf2af86bbef870f9208b85c9c7ed48",
      "manifestSha256": "aeeccc11dc6ed6f712f02c016c69ac42c05a9c64dfeab3fc34a3955037177cc8",
      "synthesisTaskId": null,
      "synthesisSats": 0,
      "nanostoreUrl": null,
      "txidsUrl": null,
      "annotatedCount": 100,
      "totalSats": 125926,
      "satsPerProof": 1259,
      "cycleWallMs": 115689,
      "cycleWallSec": 116
    },
    {
      "cycleIdx": 9,
      "cycleId": "47b4da02-009",
      "recordCount": 100,
      "scrapeWallMs": 13,
      "captainTaskId": "1b6db8c0-6dec-46f7-99bf-eb3052c2aba0",
      "captainIter": 2,
      "captainSats": 101147,
      "workerTaskId": "dc020ac0-6ec8-4ebc-b209-361c967ae970",
      "workerSats": 19355,
      "proofsCreated": 100,
      "proofErrors": 0,
      "firstTxid": "664574e02e05e398ca18ab8d3078c79916ee2bc3fa2760f3c8f20d282aee9f1e",
      "lastTxid": "d87d361b8de46870b86ab79254dfe47683fec8bf78eae7d82fdf78413a5fc55a",
      "manifestSha256": "0fe4bdeaef778f8ae3f1cb616134bbc4dac9c9a7f36bd3bc661f621f4531fcb6",
      "synthesisTaskId": null,
      "synthesisSats": 0,
      "nanostoreUrl": null,
      "txidsUrl": null,
      "annotatedCount": 100,
      "totalSats": 120502,
      "satsPerProof": 1205,
      "cycleWallMs": 133929,
      "cycleWallSec": 134
    },
    {
      "cycleIdx": 10,
      "cycleId": "47b4da02-010",
      "recordCount": 100,
      "scrapeWallMs": 10,
      "captainTaskId": "895a9672-9199-404e-a2c5-233131d92cc9",
      "captainIter": 2,
      "captainSats": 111700,
      "workerTaskId": "02366f69-e3de-4c08-b04a-60e4ecd01b71",
      "workerSats": 13854,
      "proofsCreated": 100,
      "proofErrors": 0,
      "firstTxid": "a8eec4deb5c756af755b9b6f7df305c377ad0e766090c230b0c26e89f42106b3",
      "lastTxid": "f5d876fbc68c20613cab05cf169c13d78199d6c31d0551970bfa569bb3d6b354",
      "manifestSha256": "fc674c0c5a90929820de28c6c777fd306d22c05a2db82a4c2640015abc6d8a76",
      "synthesisTaskId": null,
      "synthesisSats": 0,
      "nanostoreUrl": null,
      "txidsUrl": null,
      "annotatedCount": 100,
      "totalSats": 125554,
      "satsPerProof": 1256,
      "cycleWallMs": 134243,
      "cycleWallSec": 134
    },
    {
      "cycleIdx": 11,
      "cycleId": "47b4da02-011",
      "recordCount": 100,
      "scrapeWallMs": 11,
      "captainTaskId": "907150de-963b-46f2-b91b-11dc2e9e0ca3",
      "captainIter": 2,
      "captainSats": 99109,
      "workerTaskId": "94a55979-ee5a-45bf-bc91-2c59fdfaabc3",
      "workerSats": 14449,
      "proofsCreated": 100,
      "proofErrors": 0,
      "firstTxid": "b984e2f86dbb7335e9b01f8a44371b7a051c3242651018bf1c5c8553abd0df35",
      "lastTxid": "92d65f43b30a3e67333091d286fbbbb582392c3a183030955e28f8566542a4ae",
      "manifestSha256": "e56d0bda5fb555b6333457f6ca22dbac934f0a22f61abb06ca79a6d8c96de7f6",
      "synthesisTaskId": null,
      "synthesisSats": 0,
      "nanostoreUrl": null,
      "txidsUrl": null,
      "annotatedCount": 100,
      "totalSats": 113558,
      "satsPerProof": 1136,
      "cycleWallMs": 133902,
      "cycleWallSec": 134
    },
    {
      "cycleIdx": 12,
      "cycleId": "47b4da02-012",
      "recordCount": 100,
      "scrapeWallMs": 11,
      "captainTaskId": "46cfba7c-22b3-4db5-be67-7552c301d770",
      "captainIter": 2,
      "captainSats": 111932,
      "workerTaskId": "749f0016-79c5-4c29-b70d-d474d2d0e096",
      "workerSats": 13410,
      "proofsCreated": 100,
      "proofErrors": 0,
      "firstTxid": "7b5c622f64f558e4d566f346851746d91d596d75c4a9ac9629cb58785a4f68af",
      "lastTxid": "1c7392a279e5809d3b14f954becd3774e99a56b2c33e1517a65ce3f4b585236b",
      "manifestSha256": "8d4267649967d162d657d7d8d9050313dd2a3a70f05644687115eeb4a3c09ca8",
      "synthesisTaskId": null,
      "synthesisSats": 0,
      "nanostoreUrl": null,
      "txidsUrl": null,
      "annotatedCount": 100,
      "totalSats": 125342,
      "satsPerProof": 1253,
      "cycleWallMs": 134687,
      "cycleWallSec": 135
    },
    {
      "cycleIdx": 13,
      "cycleId": "47b4da02-013",
      "recordCount": 100,
      "scrapeWallMs": 12,
      "captainTaskId": "4c67f9b5-8f08-4130-bb42-127b237d3374",
      "captainIter": 2,
      "captainSats": 96778,
      "workerTaskId": "d7d77c99-f548-458c-aaaa-ae2425b113b9",
      "workerSats": 15273,
      "proofsCreated": 100,
      "proofErrors": 0,
      "firstTxid": "4ff1c3c696f0d77eb1a498bab7e57232d719b66b7be46042a77000a17f8259d4",
      "lastTxid": "1c1977aebd6fed910ed947c6806b69ff703aa454bed6ef9a9859b7179d7e866d",
      "manifestSha256": "c1ec76b208a83653c2cc60474ea9b4ef456aba96dfe3d3d79878c161b98522c7",
      "synthesisTaskId": null,
      "synthesisSats": 0,
      "nanostoreUrl": null,
      "txidsUrl": null,
      "annotatedCount": 100,
      "totalSats": 112051,
      "satsPerProof": 1121,
      "cycleWallMs": 124943,
      "cycleWallSec": 125
    },
    {
      "cycleIdx": 14,
      "cycleId": "47b4da02-014",
      "recordCount": 100,
      "scrapeWallMs": 11,
      "captainTaskId": "316603e6-7fb4-47ce-a4a6-8019709486a5",
      "captainIter": 2,
      "captainSats": 105926,
      "workerTaskId": "83df498e-ebf6-46f4-a280-f3e1134bb2af",
      "workerSats": 14050,
      "proofsCreated": 100,
      "proofErrors": 0,
      "firstTxid": "a832fd1463ef9ccbf9adf6a22db15f48ea5994300d66cb614e5955b66217fdee",
      "lastTxid": "0164cc6e108bfbce09be10a20e19d1678cead2ee66f3b23b2d218f9e7f825c68",
      "manifestSha256": "8e0e7e089e940d4295558e5357ba256be2f5b103d96d4e6144a84c017b0c2f17",
      "synthesisTaskId": null,
      "synthesisSats": 0,
      "nanostoreUrl": null,
      "txidsUrl": null,
      "annotatedCount": 100,
      "totalSats": 119976,
      "satsPerProof": 1200,
      "cycleWallMs": 162837,
      "cycleWallSec": 163
    },
    {
      "cycleIdx": 15,
      "cycleId": "47b4da02-015",
      "recordCount": 100,
      "scrapeWallMs": 11,
      "captainTaskId": "1a001a65-87e6-47b2-920c-b3bd6dffdf33",
      "captainIter": 2,
      "captainSats": 118285,
      "workerTaskId": "18b9d0b7-3d0c-4fcf-80a9-b1493ad0ad8c",
      "workerSats": 15945,
      "proofsCreated": 99,
      "proofErrors": 1,
      "firstTxid": "6542793c1e2d880d99ed0eac487ec79d73cc08d6657f3a4a1c0e89211c5697c2",
      "lastTxid": "f9210ce9a0dd3b86b704fb4dff387072793eac8a275afb77cc77d9d2cd79dc50",
      "manifestSha256": "486d7524915ba83934f7ca1b24c4aaa4b0c553133e3ece0d1e34f21d07373ca9",
      "synthesisTaskId": null,
      "synthesisSats": 0,
      "nanostoreUrl": null,
      "txidsUrl": null,
      "annotatedCount": 99,
      "totalSats": 134230,
      "satsPerProof": 1356,
      "cycleWallMs": 151986,
      "cycleWallSec": 152
    },
    {
      "cycleIdx": 16,
      "cycleId": "47b4da02-016",
      "recordCount": 100,
      "scrapeWallMs": 11,
      "captainTaskId": "307a0469-d364-419a-81db-b921725b9970",
      "captainIter": 2,
      "captainSats": 99283,
      "workerTaskId": "0b95a719-e922-41b6-a9e7-dc82e9dbe497",
      "workerSats": 15052,
      "proofsCreated": 100,
      "proofErrors": 0,
      "firstTxid": "9ff1dc3c901029d7bec64ae65afc456ba758d0b9f8f64ba2cd30a34a5eb111f9",
      "lastTxid": "cc7416e3df04f04a5289b4a7226b743513a09d44b4a9a24de3aab50494ce687b",
      "manifestSha256": "fcc4a6541dba744022c0210db48cd1a9eb0fc57557bfcf73b5090a8809a44de1",
      "synthesisTaskId": null,
      "synthesisSats": 0,
      "nanostoreUrl": null,
      "txidsUrl": null,
      "annotatedCount": 100,
      "totalSats": 114335,
      "satsPerProof": 1143,
      "cycleWallMs": 131452,
      "cycleWallSec": 131
    }
  ]
}