{
  "runNonce": "70f7138e",
  "mode": "POSTS_ONLY",
  "batchCap": 100,
  "soakCycles": 17,
  "successCycles": 12,
  "completedCycles": 17,
  "inProgress": false,
  "synthesisEnabled": true,
  "totalSats": 1435898,
  "totalProofs": 1200,
  "satsPerProofAvg": 1197,
  "avgCycleSats": 119658,
  "avgCycleWallSec": 169,
  "totalWallSec": 4106,
  "fatalError": null,
  "cycles": [
    {
      "cycleIdx": 0,
      "error": "task 66ee1f6e-d722-414a-82ae-46d00862cf4d did not complete before deadline"
    },
    {
      "cycleIdx": 1,
      "cycleId": "70f7138e-001",
      "recordCount": 100,
      "scrapeWallMs": 24,
      "captainTaskId": "0dc5dd2d-8227-42e4-97c5-dcd6f63d3f92",
      "captainIter": 2,
      "captainSats": 109345,
      "workerTaskId": "d738ac43-c1d9-45ee-9ec8-291f4eada5df",
      "workerSats": 16129,
      "proofsCreated": 100,
      "proofErrors": 0,
      "firstTxid": "8fa800cf93c23a216a9c2d0f0b1387befcc321299f16e7b9be4bababff815b9e",
      "lastTxid": "df975781db54d9350c13b6874185c6ce5d6097252f1aa91813700b06c3d9bea4",
      "manifestSha256": "1c4859eb07977535a8fd78f8c28c7d0d1d037f0be8f7a5dfda9911e5edaa1146",
      "synthesisTaskId": null,
      "synthesisSats": 0,
      "nanostoreUrl": null,
      "txidsUrl": null,
      "annotatedCount": 100,
      "totalSats": 125474,
      "satsPerProof": 1255,
      "cycleWallMs": 230549,
      "cycleWallSec": 231
    },
    {
      "cycleIdx": 2,
      "cycleId": "70f7138e-002",
      "recordCount": 100,
      "scrapeWallMs": 15,
      "captainTaskId": "522041cc-f6b7-4db4-9723-bd93871ef691",
      "captainIter": 2,
      "captainSats": 89418,
      "workerTaskId": "d738ac43-c1d9-45ee-9ec8-291f4eada5df",
      "workerSats": 16129,
      "proofsCreated": 100,
      "proofErrors": 0,
      "firstTxid": "8fa800cf93c23a216a9c2d0f0b1387befcc321299f16e7b9be4bababff815b9e",
      "lastTxid": "df975781db54d9350c13b6874185c6ce5d6097252f1aa91813700b06c3d9bea4",
      "manifestSha256": "1c4859eb07977535a8fd78f8c28c7d0d1d037f0be8f7a5dfda9911e5edaa1146",
      "synthesisTaskId": null,
      "synthesisSats": 0,
      "nanostoreUrl": null,
      "txidsUrl": null,
      "annotatedCount": 100,
      "totalSats": 105547,
      "satsPerProof": 1055,
      "cycleWallMs": 103838,
      "cycleWallSec": 104
    },
    {
      "cycleIdx": 3,
      "cycleId": "70f7138e-003",
      "recordCount": 100,
      "scrapeWallMs": 15,
      "captainTaskId": "6cd9fadb-f521-428a-a945-389f33baa744",
      "captainIter": 2,
      "captainSats": 102732,
      "workerTaskId": "a0360e05-9a3d-471f-8165-2ef4967aa29c",
      "workerSats": 15265,
      "proofsCreated": 100,
      "proofErrors": 0,
      "firstTxid": "a870338ead546688fa236e6dab6f5bbbfce72b894ffc3b3739e6d01f96121226",
      "lastTxid": "071c7ae195f4f524133cdd5e9a15d2a8b45f1a3e33fdd530064c0875c55e2ac3",
      "manifestSha256": "5e34f607c4f9171713e348c757cea1799c8ab1037ba57aeb8ed1394b8132dda7",
      "synthesisTaskId": null,
      "synthesisSats": 0,
      "nanostoreUrl": null,
      "txidsUrl": null,
      "annotatedCount": 100,
      "totalSats": 117997,
      "satsPerProof": 1180,
      "cycleWallMs": 300360,
      "cycleWallSec": 300
    },
    {
      "cycleIdx": 4,
      "cycleId": "70f7138e-004",
      "recordCount": 100,
      "scrapeWallMs": 18,
      "captainTaskId": "3a1023b4-dc0c-4ba3-a361-23e6659d3580",
      "captainIter": 2,
      "captainSats": 102986,
      "workerTaskId": "80a6622f-56ea-4b3a-a889-b6bf7b4967f7",
      "workerSats": 13804,
      "proofsCreated": 100,
      "proofErrors": 0,
      "firstTxid": "ca4fa57c48c07ec1e1e1096e23b485a9a0e04754e52431107ed552f5e43857cf",
      "lastTxid": "9064f4eacb64a358cdded63b1e667615c2868d15bec3a91960678fb6b8f99f2e",
      "manifestSha256": "6a455a9232c8a431d858d9dd9808beeaafcd834596a75f351a49d9c430ddad98",
      "synthesisTaskId": null,
      "synthesisSats": 0,
      "nanostoreUrl": null,
      "txidsUrl": null,
      "annotatedCount": 100,
      "totalSats": 116790,
      "satsPerProof": 1168,
      "cycleWallMs": 131980,
      "cycleWallSec": 132
    },
    {
      "cycleIdx": 5,
      "cycleId": "70f7138e-005",
      "recordCount": 100,
      "scrapeWallMs": 11,
      "captainTaskId": "94044bf0-8f1c-4ee6-9e87-8e82a4f28e9a",
      "captainIter": 2,
      "captainSats": 106026,
      "workerTaskId": "12749d4f-a073-42c1-bca5-8c5d6bad3c20",
      "workerSats": 14393,
      "proofsCreated": 100,
      "proofErrors": 0,
      "firstTxid": "9fabe2227f45a1a7a85fa11db80cbdd1ddf28df693e9898277b790325525b0e1",
      "lastTxid": "9e41ce380e953e38a1c7c964a488af058605a907dca39a8bcb4a66516ba08d10",
      "manifestSha256": "26eacdcdfad563047df649c5518cf8aa390b9ae2134357887e078413b3969cd8",
      "synthesisTaskId": null,
      "synthesisSats": 0,
      "nanostoreUrl": null,
      "txidsUrl": null,
      "annotatedCount": 100,
      "totalSats": 120419,
      "satsPerProof": 1204,
      "cycleWallMs": 182364,
      "cycleWallSec": 182
    },
    {
      "cycleIdx": 6,
      "cycleId": "70f7138e-006",
      "recordCount": 100,
      "scrapeWallMs": 12,
      "captainTaskId": "62c742d7-5050-4f6d-a7bf-04714efea868",
      "captainIter": 2,
      "captainSats": 113361,
      "workerTaskId": "1f455d55-11db-43d7-a3cb-ac59c159fad3",
      "workerSats": 13999,
      "proofsCreated": 100,
      "proofErrors": 0,
      "firstTxid": "5aa20eebf5f348a0c1fb63cb9d7b57aefae2e36905b99ae1e3cc495649fb22f4",
      "lastTxid": "b12c886c9a9edc5826347e4dd78f9690fefc17c882ad03851eab0420d447f36a",
      "manifestSha256": "7f3d04aafba2f7ceacc7027bc70e91a2604ca105dfc5e6e033c7f0255a42125a",
      "synthesisTaskId": null,
      "synthesisSats": 0,
      "nanostoreUrl": null,
      "txidsUrl": null,
      "annotatedCount": 100,
      "totalSats": 127360,
      "satsPerProof": 1274,
      "cycleWallMs": 175084,
      "cycleWallSec": 175
    },
    {
      "cycleIdx": 7,
      "cycleId": "70f7138e-007",
      "recordCount": 100,
      "scrapeWallMs": 16,
      "captainTaskId": "c3c791f3-ab31-4e5c-8308-abd682367d83",
      "captainIter": 2,
      "captainSats": 101696,
      "workerTaskId": "fd6d0f7d-faca-4876-b7c5-be9cfefd8d5e",
      "workerSats": 17382,
      "proofsCreated": 100,
      "proofErrors": 0,
      "firstTxid": "36487ad7192ab6b06069723aa2b01d5f664962092a0d20f8946a049aa96cf566",
      "lastTxid": "efef66bd2154ef62ad7dcd15593d0419d7b80cdf1e419fea22165669bc9962c3",
      "manifestSha256": "e1f67743072f2d97838997bedc5018400045f6eff64c709dd7850e7f6ba0acd5",
      "synthesisTaskId": null,
      "synthesisSats": 0,
      "nanostoreUrl": null,
      "txidsUrl": null,
      "annotatedCount": 100,
      "totalSats": 119078,
      "satsPerProof": 1191,
      "cycleWallMs": 103466,
      "cycleWallSec": 103
    },
    {
      "cycleIdx": 8,
      "cycleId": "70f7138e-008",
      "recordCount": 100,
      "scrapeWallMs": 12,
      "captainTaskId": "0ca0184f-6208-4b44-9da9-3a6a24497053",
      "captainIter": 2,
      "captainSats": 114689,
      "workerTaskId": "c6a5fc8e-8159-4f38-86b5-9ca0f2ede7bb",
      "workerSats": 18064,
      "proofsCreated": 100,
      "proofErrors": 0,
      "firstTxid": "1700157bf6f2229eca528acbd237651abed43347ca1ca7705983a63a0de4e44b",
      "lastTxid": "11fa06702718f9c01f98ce430931cea03e6ae87d58e9b800cc680af487be537f",
      "manifestSha256": "24a2d83f52fc6a1e08af45fe239fefb87aede1130e5e0651eb4c4f899d164566",
      "synthesisTaskId": null,
      "synthesisSats": 0,
      "nanostoreUrl": null,
      "txidsUrl": null,
      "annotatedCount": 100,
      "totalSats": 132753,
      "satsPerProof": 1328,
      "cycleWallMs": 187917,
      "cycleWallSec": 188
    },
    {
      "cycleIdx": 9,
      "cycleId": "70f7138e-009",
      "recordCount": 100,
      "scrapeWallMs": 22,
      "captainTaskId": "4660a65d-9f77-468d-99ed-c41bb3561cf5",
      "captainIter": 2,
      "captainSats": 108048,
      "workerTaskId": "2f2c26cd-2955-4783-898c-65b66cfcdd75",
      "workerSats": 13519,
      "proofsCreated": 100,
      "proofErrors": 0,
      "firstTxid": "0702f52b98b65a181d17f5c7273e4806709a9c08fde19778a299fcf7daf00352",
      "lastTxid": "3eb753ba7521d7aeba245c4489063bcb2c7db26eba917e43bf37bc8a1104d7c1",
      "manifestSha256": "81444d464a437e93160e807c0eb679c26d4e206249917e45958e252bbc17493f",
      "synthesisTaskId": null,
      "synthesisSats": 0,
      "nanostoreUrl": null,
      "txidsUrl": null,
      "annotatedCount": 100,
      "totalSats": 121567,
      "satsPerProof": 1216,
      "cycleWallMs": 144022,
      "cycleWallSec": 144
    },
    {
      "cycleIdx": 10,
      "cycleId": "70f7138e-010",
      "recordCount": 100,
      "scrapeWallMs": 11,
      "captainTaskId": "e9236622-d273-4dfa-8142-7465b61efd77",
      "captainIter": 2,
      "captainSats": 107959,
      "workerTaskId": "7aee1486-9982-4f59-b064-8e6d745cf2a6",
      "workerSats": 14752,
      "proofsCreated": 100,
      "proofErrors": 0,
      "firstTxid": "c08723ae388e87e9d18e89011b31585eeaa0eca3bb0e8517f06aacb96218f86b",
      "lastTxid": "9f78dd6a30260a235ab6801037ac8cfb90ecda02ecd29847be2901877abb2e28",
      "manifestSha256": "c3538c3e3f48b06305df5fa70ce8f45834790fa9a7c9665ddb022cef080d1ba2",
      "synthesisTaskId": null,
      "synthesisSats": 0,
      "nanostoreUrl": null,
      "txidsUrl": null,
      "annotatedCount": 100,
      "totalSats": 122711,
      "satsPerProof": 1227,
      "cycleWallMs": 131539,
      "cycleWallSec": 132
    },
    {
      "cycleIdx": 11,
      "cycleId": "70f7138e-011",
      "recordCount": 100,
      "scrapeWallMs": 12,
      "captainTaskId": "3e4e6af6-7494-41e3-9186-aa287d779873",
      "captainIter": 2,
      "captainSats": 96064,
      "workerTaskId": "e6edb94a-12ed-4732-b2c0-bb653d3f891c",
      "workerSats": 13895,
      "proofsCreated": 100,
      "proofErrors": 0,
      "firstTxid": "4238379e9112daa9e3a9e91826d91cfb880e19404877638ca5e1bb38d0c5bd3f",
      "lastTxid": "914391da891cc85c111dd96073ce577a304a2372f54c5c772d79ab85d6893c04",
      "manifestSha256": "220bf004202077cbc0255314a4603222aa5d51839830bc8ddcbfc537c7561401",
      "synthesisTaskId": null,
      "synthesisSats": 0,
      "nanostoreUrl": null,
      "txidsUrl": null,
      "annotatedCount": 100,
      "totalSats": 109959,
      "satsPerProof": 1100,
      "cycleWallMs": 102883,
      "cycleWallSec": 103
    },
    {
      "cycleIdx": 12,
      "cycleId": "70f7138e-012",
      "recordCount": 100,
      "scrapeWallMs": 43,
      "captainTaskId": "7897761f-8b21-42de-a81a-7a4f02f0b3d6",
      "captainIter": 2,
      "captainSats": 101905,
      "workerTaskId": "dd28e1fd-61fd-445e-9741-a167fae7e3c7",
      "workerSats": 14338,
      "proofsCreated": 100,
      "proofErrors": 0,
      "firstTxid": "d19b1a7502d72aeaa18decc5627db5125cb85fe1514ac6b87efb2d36100ead06",
      "lastTxid": "a63e997cba85e24314e8ee2bdec713d9cc52a0964fdc3f1d8e66f3d95887c654",
      "manifestSha256": "8cfb6793c68bcb49569e7b6a14da361ce6de971c8cfade0a7381293abafff071",
      "synthesisTaskId": null,
      "synthesisSats": 0,
      "nanostoreUrl": null,
      "txidsUrl": null,
      "annotatedCount": 100,
      "totalSats": 116243,
      "satsPerProof": 1162,
      "cycleWallMs": 233254,
      "cycleWallSec": 233
    },
    {
      "cycleIdx": 13,
      "error": "task 1fa3a896-e4d6-442f-9325-118098859ff3 did not complete before deadline"
    },
    {
      "cycleIdx": 14,
      "error": "submit failed: HTTP 401 \"\""
    },
    {
      "cycleIdx": 15,
      "error": "submit failed: HTTP 401 \"\""
    },
    {
      "cycleIdx": 16,
      "error": "submit failed: HTTP 401 \"\""
    }
  ]
}