{
  "runNonce": "d800cc72",
  "mode": "POSTS_ONLY",
  "batchCap": 100,
  "soakCycles": 17,
  "successCycles": 13,
  "completedCycles": 17,
  "inProgress": false,
  "synthesisEnabled": true,
  "totalSats": 1597308,
  "totalProofs": 1300,
  "satsPerProofAvg": 1229,
  "avgCycleSats": 122870,
  "avgCycleWallSec": 151,
  "totalWallSec": 4040,
  "fatalError": null,
  "cycles": [
    {
      "cycleIdx": 0,
      "error": "task 8f7c9e7a-12c6-4062-8f6a-a444d3a9ed2a did not complete before deadline"
    },
    {
      "cycleIdx": 1,
      "cycleId": "d800cc72-001",
      "recordCount": 100,
      "scrapeWallMs": 15,
      "captainTaskId": "9e976b42-0dbe-4337-985c-a5b79f1aafba",
      "captainIter": 2,
      "captainSats": 95208,
      "workerTaskId": "66310c89-fd57-4336-9d88-725df5665bfa",
      "workerSats": 14179,
      "proofsCreated": 100,
      "proofErrors": 0,
      "firstTxid": "241cff9fb64a70348050f2a24c1e3f888f98c494437fdce2477febae5ed46533",
      "lastTxid": "29e8091d86e250a2daa10f68bf81b5f4acf52b0e45c9987230c6a16760b3b858",
      "manifestSha256": "2a91333eaaa02216ba91ee095221419146d0297cb0496b8bf1a6d2be7de523eb",
      "synthesisTaskId": null,
      "synthesisSats": 0,
      "nanostoreUrl": null,
      "txidsUrl": null,
      "annotatedCount": 100,
      "totalSats": 109387,
      "satsPerProof": 1094,
      "cycleWallMs": 256672,
      "cycleWallSec": 257
    },
    {
      "cycleIdx": 2,
      "cycleId": "d800cc72-002",
      "recordCount": 100,
      "scrapeWallMs": 13,
      "captainTaskId": "eb62b6be-7b3e-4c3d-9d35-e267f7c7a0b3",
      "captainIter": 2,
      "captainSats": 111742,
      "workerTaskId": "66310c89-fd57-4336-9d88-725df5665bfa",
      "workerSats": 14179,
      "proofsCreated": 100,
      "proofErrors": 0,
      "firstTxid": "241cff9fb64a70348050f2a24c1e3f888f98c494437fdce2477febae5ed46533",
      "lastTxid": "29e8091d86e250a2daa10f68bf81b5f4acf52b0e45c9987230c6a16760b3b858",
      "manifestSha256": "2a91333eaaa02216ba91ee095221419146d0297cb0496b8bf1a6d2be7de523eb",
      "synthesisTaskId": null,
      "synthesisSats": 0,
      "nanostoreUrl": null,
      "txidsUrl": null,
      "annotatedCount": 100,
      "totalSats": 125921,
      "satsPerProof": 1259,
      "cycleWallMs": 113484,
      "cycleWallSec": 113
    },
    {
      "cycleIdx": 3,
      "cycleId": "d800cc72-003",
      "recordCount": 100,
      "scrapeWallMs": 14,
      "captainTaskId": "43c5377e-240f-4b76-9c5a-d8f2e9e4b00d",
      "captainIter": 2,
      "captainSats": 113819,
      "workerTaskId": "f0bb36ae-9e82-4ff6-a1a6-9119b488876c",
      "workerSats": 22365,
      "proofsCreated": 100,
      "proofErrors": 0,
      "firstTxid": "56e7d91243fd69147492820389728294557fe1305948009d6eaf0fbd512b0a30",
      "lastTxid": "00d7000786a561366293459745b44ad50e2db6f6ba622df9aa14b75dec9c3649",
      "manifestSha256": "b09dae750d1002d5dbdfe49cee536ac218291e087d0b349583f20d8fd851f550",
      "synthesisTaskId": null,
      "synthesisSats": 0,
      "nanostoreUrl": null,
      "txidsUrl": null,
      "annotatedCount": 100,
      "totalSats": 136184,
      "satsPerProof": 1362,
      "cycleWallMs": 134907,
      "cycleWallSec": 135
    },
    {
      "cycleIdx": 4,
      "cycleId": "d800cc72-004",
      "recordCount": 100,
      "scrapeWallMs": 28,
      "captainTaskId": "5a89abff-8990-475f-9cdc-f3bbbe8c0422",
      "captainIter": 2,
      "captainSats": 110016,
      "workerTaskId": "f0bb36ae-9e82-4ff6-a1a6-9119b488876c",
      "workerSats": 22365,
      "proofsCreated": 100,
      "proofErrors": 0,
      "firstTxid": "56e7d91243fd69147492820389728294557fe1305948009d6eaf0fbd512b0a30",
      "lastTxid": "00d7000786a561366293459745b44ad50e2db6f6ba622df9aa14b75dec9c3649",
      "manifestSha256": "b09dae750d1002d5dbdfe49cee536ac218291e087d0b349583f20d8fd851f550",
      "synthesisTaskId": null,
      "synthesisSats": 0,
      "nanostoreUrl": null,
      "txidsUrl": null,
      "annotatedCount": 100,
      "totalSats": 132381,
      "satsPerProof": 1324,
      "cycleWallMs": 104751,
      "cycleWallSec": 105
    },
    {
      "cycleIdx": 5,
      "cycleId": "d800cc72-005",
      "recordCount": 100,
      "scrapeWallMs": 12,
      "captainTaskId": "ef727e07-ea77-429c-a9fe-55662af5069d",
      "captainIter": 2,
      "captainSats": 97097,
      "workerTaskId": "0addfaba-07a2-4d96-ad44-538b2a311087",
      "workerSats": 14223,
      "proofsCreated": 100,
      "proofErrors": 0,
      "firstTxid": "ffcbc50489d8aa4fbea23ead1c7f5b44ed0fb362205bba3ec84980bd17d15452",
      "lastTxid": "8313cec8db65626e2052cbdacadc23418666add69cbf9ab1827ba3779097251c",
      "manifestSha256": "c22082d9d910141ee1cda7b6db59463d47794ff12ab225438dffebbcc4e4a589",
      "synthesisTaskId": null,
      "synthesisSats": 0,
      "nanostoreUrl": null,
      "txidsUrl": null,
      "annotatedCount": 100,
      "totalSats": 111320,
      "satsPerProof": 1113,
      "cycleWallMs": 206333,
      "cycleWallSec": 206
    },
    {
      "cycleIdx": 6,
      "cycleId": "d800cc72-006",
      "recordCount": 100,
      "scrapeWallMs": 11,
      "captainTaskId": "e78a38e2-fce1-492b-a9ac-498eb431cf5a",
      "captainIter": 2,
      "captainSats": 111419,
      "workerTaskId": "c418e94c-8776-4f99-a0bc-0fc1676f5f73",
      "workerSats": 14535,
      "proofsCreated": 100,
      "proofErrors": 0,
      "firstTxid": "36d8514b48df69b714c0a152068b29afa994a589d0621809170297dd70472f2d",
      "lastTxid": "7f4e5a978f39b33e98c64c09022d1606def5b3b593dd5ff90be69521a6569833",
      "manifestSha256": "d7a8a91939e20bb7cf342ec0084e978749d1435bf610f2c9b3dc296c9f241017",
      "synthesisTaskId": null,
      "synthesisSats": 0,
      "nanostoreUrl": null,
      "txidsUrl": null,
      "annotatedCount": 100,
      "totalSats": 125954,
      "satsPerProof": 1260,
      "cycleWallMs": 101974,
      "cycleWallSec": 102
    },
    {
      "cycleIdx": 7,
      "cycleId": "d800cc72-007",
      "recordCount": 100,
      "scrapeWallMs": 12,
      "captainTaskId": "e793e570-0a72-4466-bdcc-29a8f2934840",
      "captainIter": 2,
      "captainSats": 112677,
      "workerTaskId": "b6dd5ce1-556e-4823-a0c4-aa813ca37747",
      "workerSats": 15047,
      "proofsCreated": 100,
      "proofErrors": 0,
      "firstTxid": "1738c1e7ec8d2c29815f27a06903c47900db0a75b57d0f878cceae7bdae483b8",
      "lastTxid": "54e3a348961dc8f52cd5ff6e5876342d715273df26a2c3931dce8924f2b23fa0",
      "manifestSha256": "9132af6b0022dde61dad96499af279d0892dbaf7d89c215335552957526d3bba",
      "synthesisTaskId": null,
      "synthesisSats": 0,
      "nanostoreUrl": null,
      "txidsUrl": null,
      "annotatedCount": 100,
      "totalSats": 127724,
      "satsPerProof": 1277,
      "cycleWallMs": 172170,
      "cycleWallSec": 172
    },
    {
      "cycleIdx": 8,
      "cycleId": "d800cc72-008",
      "recordCount": 100,
      "scrapeWallMs": 11,
      "captainTaskId": "489ac546-4713-4cd7-aaf9-cceaef5c350b",
      "captainIter": 2,
      "captainSats": 108421,
      "workerTaskId": "f9e8efd6-dc1d-49b3-be61-d88b44f73a44",
      "workerSats": 15697,
      "proofsCreated": 100,
      "proofErrors": 0,
      "firstTxid": "6aa42d13ee30d4160b1eacfc537a9c0dcb18c2f177b5132a360bb773924d067a",
      "lastTxid": "769f78cc3c78302665a9629ca7f1668cf0bc20f3744d6a4bde510136c8c8aab5",
      "manifestSha256": "ea2faf5f1900e5f3545dd9c51d7bed3133aaefdf79c7a51b6c1aac27d7832031",
      "synthesisTaskId": null,
      "synthesisSats": 0,
      "nanostoreUrl": null,
      "txidsUrl": null,
      "annotatedCount": 100,
      "totalSats": 124118,
      "satsPerProof": 1241,
      "cycleWallMs": 140557,
      "cycleWallSec": 141
    },
    {
      "cycleIdx": 9,
      "cycleId": "d800cc72-009",
      "recordCount": 100,
      "scrapeWallMs": 15,
      "captainTaskId": "65a8763d-545c-40d0-81e8-e60a0a463892",
      "captainIter": 2,
      "captainSats": 102118,
      "workerTaskId": "4ec036ff-fc28-4858-9ea6-79130057565e",
      "workerSats": 13292,
      "proofsCreated": 100,
      "proofErrors": 0,
      "firstTxid": "f141355f6c41beef7becf10283709c13c9aa8a9456796a129ddffbbaf990eabb",
      "lastTxid": "5ffd087389e40ae0978cfa72249280c6cc2b10f3e14a639e1e1cbf8e6a7619cd",
      "manifestSha256": "e35abcf48f8d46ca7f816b6651bd5a88271409cb678baf99c4d24092917afd0c",
      "synthesisTaskId": null,
      "synthesisSats": 0,
      "nanostoreUrl": null,
      "txidsUrl": null,
      "annotatedCount": 100,
      "totalSats": 115410,
      "satsPerProof": 1154,
      "cycleWallMs": 118557,
      "cycleWallSec": 119
    },
    {
      "cycleIdx": 10,
      "cycleId": "d800cc72-010",
      "recordCount": 100,
      "scrapeWallMs": 18,
      "captainTaskId": "aaa5544b-f149-46f0-aa70-dce7bf6f45c3",
      "captainIter": 2,
      "captainSats": 102730,
      "workerTaskId": "7f9f67ba-0cef-4031-a327-bfc849a7dc74",
      "workerSats": 14673,
      "proofsCreated": 100,
      "proofErrors": 0,
      "firstTxid": "a5ba06512803bf680b27bb8adce97cfa969e56cecfd5faafe2c96def8c98cec9",
      "lastTxid": "4ed0a46a1045bec8c32f820119a34f6ba69aa4a79e2802d2008c864ea62c0b38",
      "manifestSha256": "446d13917141d7c333c67a83306a1a1f12be4463ddc0170b3ac553edb55454c7",
      "synthesisTaskId": null,
      "synthesisSats": 0,
      "nanostoreUrl": null,
      "txidsUrl": null,
      "annotatedCount": 100,
      "totalSats": 117403,
      "satsPerProof": 1174,
      "cycleWallMs": 134354,
      "cycleWallSec": 134
    },
    {
      "cycleIdx": 11,
      "cycleId": "d800cc72-011",
      "recordCount": 100,
      "scrapeWallMs": 13,
      "captainTaskId": "3703e004-b4a9-4be5-92c0-3bf16b5a79e4",
      "captainIter": 2,
      "captainSats": 120169,
      "workerTaskId": "d31e3666-688e-40c9-82a0-483280a6b297",
      "workerSats": 16765,
      "proofsCreated": 100,
      "proofErrors": 0,
      "firstTxid": "b99f120ce2e45b4d518134a04bf238f34c8053e15fd7cd99a80699eac9ce987d",
      "lastTxid": "f4c387a1b3a33e1208051a8072ebb52e5e256b887a2befc05868e85a772a01a0",
      "manifestSha256": "fef211e3ebdd862649c789f6f65e4df618d60e32af792f95306f7e963433aa3a",
      "synthesisTaskId": null,
      "synthesisSats": 0,
      "nanostoreUrl": null,
      "txidsUrl": null,
      "annotatedCount": 100,
      "totalSats": 136934,
      "satsPerProof": 1369,
      "cycleWallMs": 140810,
      "cycleWallSec": 141
    },
    {
      "cycleIdx": 12,
      "cycleId": "d800cc72-012",
      "recordCount": 100,
      "scrapeWallMs": 12,
      "captainTaskId": "89d2f973-7d5f-4274-b356-e7929d8e2e4e",
      "captainIter": 2,
      "captainSats": 103452,
      "workerTaskId": "476234e6-6d9a-4be5-947e-baf25c22b5bd",
      "workerSats": 15114,
      "proofsCreated": 100,
      "proofErrors": 0,
      "firstTxid": "d0af65f993dedf86be213220c20d2a42ff0c232ea5875263fd17efadfcf5ea07",
      "lastTxid": "bf2629772356af4fa0e7a0efb9f04c47cd5d1868df80fca9775621eaf4d58ab4",
      "manifestSha256": "e6dd4a5c277301660747a6f1f502c6bb8a9c72f2df0e68c11e35572210ee20dc",
      "synthesisTaskId": null,
      "synthesisSats": 0,
      "nanostoreUrl": null,
      "txidsUrl": null,
      "annotatedCount": 100,
      "totalSats": 118566,
      "satsPerProof": 1186,
      "cycleWallMs": 142230,
      "cycleWallSec": 142
    },
    {
      "cycleIdx": 13,
      "cycleId": "d800cc72-013",
      "recordCount": 100,
      "scrapeWallMs": 16,
      "captainTaskId": "067bee6f-6aa4-40c8-b705-722bc3ab1819",
      "captainIter": 2,
      "captainSats": 102311,
      "workerTaskId": "bfba4173-bc54-49c4-9f27-716ee1c59eee",
      "workerSats": 13695,
      "proofsCreated": 100,
      "proofErrors": 0,
      "firstTxid": "4e29382a0ead6b1ad6fd77de2b3979a7f46b526b3c7cc22a222717e615b05259",
      "lastTxid": "42bc1a1579d9423702d9d71b0998e2ab0dd3708379996b7c91eaa3ec3453aed9",
      "manifestSha256": "97d780e0eaf476ca32a5e60b87adb6d5310a255e8e4fb6d77713ad4e18f88a7c",
      "synthesisTaskId": null,
      "synthesisSats": 0,
      "nanostoreUrl": null,
      "txidsUrl": null,
      "annotatedCount": 100,
      "totalSats": 116006,
      "satsPerProof": 1160,
      "cycleWallMs": 192559,
      "cycleWallSec": 193
    },
    {
      "cycleIdx": 14,
      "error": "task ab6bd347-3ef9-41cc-b141-339c99ffcc62 did not complete before deadline"
    },
    {
      "cycleIdx": 15,
      "error": "submit failed: HTTP 401 \"\""
    },
    {
      "cycleIdx": 16,
      "error": "submit failed: HTTP 401 \"\""
    }
  ]
}